{
    "wire-plugin": [
        {
            "target": "\\Spryker\\Glue\\CartsRestApi\\CartsRestApiDependencyProvider::getRestCartAttributesMapperPlugins",
            "source": "\\Spryker\\Glue\\SalesOrderThresholdsRestApi\\Plugin\\CartsRestApi\\SalesOrderThresholdRestCartAttributesMapperPlugin"
        },
        {
            "target": "\\Spryker\\Zed\\CartsRestApi\\CartsRestApiDependencyProvider::getQuoteExpanderPlugins",
            "source": "\\Spryker\\Zed\\SalesOrderThresholdsRestApi\\Communication\\Plugin\\CartsRestApi\\SalesOrderThresholdQuoteExpanderPlugin"
        },
        {
            "target": "\\Spryker\\Zed\\CheckoutRestApi\\CheckoutRestApiDependencyProvider::getReadCheckoutDataValidatorPlugins",
            "source": "\\Spryker\\Zed\\SalesOrderThresholdsRestApi\\Communication\\Plugin\\CheckoutRestApi\\SalesOrderThresholdReadCheckoutDataValidatorPlugin"
        }
    ]
}
