{
    "wire-plugin": [
        {
            "target": "\\Spryker\\Glue\\GlueApplication\\GlueApplicationDependencyProvider::getResourceRoutePlugins",
            "source": "\\Spryker\\Glue\\SalesReturnsRestApi\\Plugin\\ReturnReasonsResourceRoutePlugin"
        },
        {
            "target": "\\Spryker\\Glue\\GlueApplication\\GlueApplicationDependencyProvider::getResourceRoutePlugins",
            "source": "\\Spryker\\Glue\\SalesReturnsRestApi\\Plugin\\ReturnsResourceRoutePlugin"
        }
    ],
    "wire-glue-relationship": [
        {
            "source": {
                "\\Spryker\\Glue\\SalesReturnsRestApi\\SalesReturnsRestApiConfig::RESOURCE_RETURNS": "\\Spryker\\Glue\\SalesReturnsRestApi\\Plugin\\ReturnItemByReturnResourceRelationshipPlugin"
            }
        }
    ]
}
